pxplore.py
pxplore-0.2.0.dist-info/LICENSE
pxplore-0.2.0.dist-info/WHEEL
pxplore-0.2.0.dist-info/METADATA
pxplore-0.2.0.dist-info/RECORD
